LICENSE
README.md
setup.py
MorphologicalDisambiguation/AutoDisambiguator.py
MorphologicalDisambiguation/DummyDisambiguation.py
MorphologicalDisambiguation/HmmDisambiguation.py
MorphologicalDisambiguation/LongestRootFirstDisambiguation.py
MorphologicalDisambiguation/MorphologicalDisambiguator.py
MorphologicalDisambiguation/NaiveDisambiguation.py
MorphologicalDisambiguation/RootFirstDisambiguation.py
MorphologicalDisambiguation/__init__.py
MorphologicalDisambiguation/data/__init__.py
MorphologicalDisambiguation/data/rootlist.txt
NlpToolkit_MorphologicalDisambiguation.egg-info/PKG-INFO
NlpToolkit_MorphologicalDisambiguation.egg-info/SOURCES.txt
NlpToolkit_MorphologicalDisambiguation.egg-info/dependency_links.txt
NlpToolkit_MorphologicalDisambiguation.egg-info/requires.txt
NlpToolkit_MorphologicalDisambiguation.egg-info/top_level.txt