Metadata-Version: 2.1
Name: NlpToolkit-MorphologicalDisambiguation
Version: 1.0.17
Summary: Turkish Morphological Disambiguation Library
Home-page: https://github.com/StarlangSoftware/TurkishMorphologicalDisambiguation-Py
Author: olcaytaner
Author-email: olcay.yildiz@ozyegin.edu.tr
License: UNKNOWN
Platform: UNKNOWN
